dillo/__init__.py
dillo/dillo.py
dillo/signing.py
dill_o-0.2.1.dist-info/LICENSE
dill_o-0.2.1.dist-info/WHEEL
dill_o-0.2.1.dist-info/METADATA
dill_o-0.2.1.dist-info/RECORD
